transcribe/__init__.py
transcribe/admin.py
transcribe/api.py
transcribe/apps.py
transcribe/diff_match_patch.py
transcribe/filters.py
transcribe/forms.py
transcribe/middleware.py
transcribe/models.py
transcribe/settings.py
transcribe/signals.py
transcribe/urls.py
transcribe/utils.py
transcribe/management/__init__.py
transcribe/management/commands/__init__.py
transcribe/management/commands/check_media_size.py
transcribe/management/commands/fix_permissions.py
transcribe/management/commands/functional_tests.py
transcribe/migrations/0001_initial.py
transcribe/migrations/0001_initial_squashed_0021_point_fks_to_transcribe_user.py
transcribe/migrations/0002_initial_data.py
transcribe/migrations/0003_transcribeuser.py
transcribe/migrations/0004_auto_20150716_1639.py
transcribe/migrations/0005_auto_20150717_0829.py
transcribe/migrations/0006_project_archived.py
transcribe/migrations/0007_reviewer_group_addition.py
transcribe/migrations/0008_auto_20150925_1522.py
transcribe/migrations/0009_auto_20150929_1314.py
transcribe/migrations/0010_userprojectpreferences.py
transcribe/migrations/0011_project_finding_aid_url.py
transcribe/migrations/0012_auto_20160107_1410.py
transcribe/migrations/0013_userpreferences.py
transcribe/migrations/0014_auto_20160203_1544.py
transcribe/migrations/0015_auto_20160309_1342.py
transcribe/migrations/0016_auto_20160817_1343.py
transcribe/migrations/0017_auto_20191115_1123.py
transcribe/migrations/0018_point_fks_to_user.py
transcribe/migrations/0019_create_transcribeuser.py
transcribe/migrations/0020_populate_transcribe_users.py
transcribe/migrations/0021_point_fks_to_transcribe_user.py
transcribe/migrations/__init__.py
transcribe/static/transcribe/favicon.ico
transcribe/static/transcribe/css/icons.css
transcribe/static/transcribe/css/icons.css.map
transcribe/static/transcribe/css/reset.css
transcribe/static/transcribe/css/reset.css.map
transcribe/static/transcribe/css/style.css
transcribe/static/transcribe/css/style.css.map
django_transcribe-0.8.6.dist-info/AUTHORS
django_transcribe-0.8.6.dist-info/LICENSE
django_transcribe-0.8.6.dist-info/METADATA
django_transcribe-0.8.6.dist-info/WHEEL
django_transcribe-0.8.6.dist-info/top_level.txt
django_transcribe-0.8.6.dist-info/RECORD
