Metadata-Version: 2.1
Name: django-transcribe
Version: 0.8.6
Summary: crowd source transcription
Home-page: https://gitlab.com/byuhbll/lib/python/django-transcribe
Author: BYU Library Software Engineering
Author-email: support@lib.byu.edu
Classifier: Intended Audience :: Developers
Classifier: License :: OSI Approved :: BSD License
Classifier: Operating System :: OS Independent
Classifier: Framework :: Django
Classifier: Framework :: Django :: 3.2
Classifier: Framework :: Django :: 4.1
Classifier: Framework :: Django :: 4.2
Classifier: Programming Language :: Python
Classifier: Programming Language :: Python :: 3.8
Classifier: Programming Language :: Python :: 3.9
Classifier: Programming Language :: Python :: 3.10
Classifier: Programming Language :: Python :: 3.11
Classifier: Programming Language :: Python :: 3.12
License-File: LICENSE
License-File: AUTHORS
Requires-Dist: django-model-utils
Requires-Dist: lxml
Requires-Dist: Django <5.0.0,>=3.2.0
